gridmeter/__init__.py
gridmeter/__version__.py
gridmeter/bin_selection.py
gridmeter/bins.py
gridmeter/diagnostics.py
gridmeter/distance_calc_selection.py
gridmeter/equivalence.py
gridmeter/model.py
gridmeter/param_selection.py
gridmeter/synthetic_data.py
gridmeter-1.1.0.dist-info/LICENSE
gridmeter-1.1.0.dist-info/METADATA
gridmeter-1.1.0.dist-info/WHEEL
gridmeter-1.1.0.dist-info/top_level.txt
gridmeter-1.1.0.dist-info/RECORD
