Metadata-Version: 2.1
Name: gridmeter
Version: 1.1.0
Summary: Tools for stratified sampling for comparison groups
Home-page: http://github.com/recurve-methods/comparison_groups
Author: Recurve Analytics, Inc
License: UNKNOWN
Platform: UNKNOWN
Requires-Dist: pandas (>=1.1.0)
Requires-Dist: plotnine
Provides-Extra: off-dataflow
